{
	"pages": [ //pages数组中第一项表示应用启动页，参考：https://uniapp.dcloud.io/collocation/pages
		{
			"path": "pages/login/pwd-login",
			"style": {
				"navigationBarTitleText": "",
				"app-plus": {
					"scrollIndicator": "none",
					"bounce": "vertical"
				}
			}
		},
		{
			"path": "pages/login/tel-login",
			"style": {
				"navigationBarTitleText": "",
				"app-plus": {
					"scrollIndicator": "none",
					"bounce": "vertical"
				}
			}
		}, {
			"path": "pages/login/retrieve-password",
			"style": {
				"navigationBarTitleText": "找回密码",
				"app-plus": {
					"scrollIndicator": "none",
					"bounce": "vertical"
				}
			}
		}, {
			"path": "pages/login/change-password",
			"style": {
				"navigationBarTitleText": "修改密码",
				"app-plus": {
					"scrollIndicator": "none",
					"bounce": "vertical"
				}
			}
		}, {
			"path": "pages/login/reset-password",
			"style": {
				"navigationBarTitleText": "重置密码",
				"app-plus": {
					"scrollIndicator": "none",
					"bounce": "vertical"
				}
			}
		},
		{
			"path": "pages/tabbar/index",
			"style": {
				"enablePullDownRefresh": true, //下拉刷新
				"navigationBarTitleText": "", //导航栏文字类容
				"navigationBarBackgroundColor": "#1c1a4e",
				"navigationBarTextStyle": "white",
				"app-plus": {
					"scrollIndicator":"none",
					"titleNView": {
						"searchInput": {
							"backgroundColor": "#fff",
							"placeholder": "输入关键词",
							"placeholderColor": "#b2b2b2",
							"borderRadius": "15px"
						},
						"buttons": [{
								"color": "rgba(0, 0, 0, 0)",
								"float": "left",
								"text": "1"
							},
							{
								"fontSrc": "/static/font/iconfont.ttf",
								"text": "\ue7b1",
								"fontSize": "27",
								"color": "#fff",
								"background": "rgba(0,0,0,0)",
								// "redDot": true,
								"width": "60px"
							},
							{
								"fontSrc": "",
								"text": "",
								"fontSize": "27",
								"background": "rgba(0,0,0,0)",
								"width": "10px"
							}
						]
					}
				}
			}
		}, {
			"path": "pages/tabbar/vip",
			"style": {
				"navigationStyle":"custom",
				"app-plus": {
					"scrollIndicator": "none",
					"bounce": "vertical"
				}
			}
		}, {
			"path": "pages/tabbar/msg",
			"style": {
				"navigationBarTitleText": "消息中心",
				"app-plus": {
					"scrollIndicator": "none",
					"bounce": "vertical"
				}
			}
		}, {
			"path": "pages/tabbar/profile",
			"style": {
				"navigationBarTitleText": "个人中心",
				"navigationBarBackgroundColor": "#1b2664",
				"navigationBarTextStyle": "white",
				"app-plus": {
					"scrollIndicator":"none",
					"titleNView": {
						"buttons": [{
							"text": "帮助中心", //原生标题栏增加分享按钮，点击事件可通过页面的 onNavigationBarButtonTap 函数进行监听
							"fontSize": "26upx",
							"color": "#fff",
							"width": "150upx"
						}]
					}
				}
			}
		}, {
			"path": "pages/profile/personal-information",
			"style": {
				"navigationBarTitleText": "个人信息",
				"app-plus": {
					"scrollIndicator": "none",
					"bounce": "vertical"
				}
			}
		}, {
			"path": "pages/profile/change-password",
			"style": {
				"navigationBarTitleText": "修改密码",
				"app-plus": {
					"scrollIndicator": "none",
					"bounce": "vertical"
				}
			}
		}, {
			"path": "pages/profile/withdrawal",
			"style": {
				"navigationBarTitleText": "申请提现",
				"app-plus": {
					"scrollIndicator":"none",
					"titleNView": {
						"buttons": [{
							"text": "提现记录", //原生标题栏增加分享按钮，点击事件可通过页面的 onNavigationBarButtonTap 函数进行监听
							"fontSize": "26upx",
							"color": "#808080",
							"width": "150upx"
						}]
					}
				}
			}
		}, {
			"path": "pages/profile/my-team",
			"style": {
				"navigationBarTitleText": "我的团队",
				"app-plus": {
					"scrollIndicator": "none",
					"bounce": "vertical"
				}
			}
		}, {
			"path": "pages/profile/my-credit",
			"style": {
				"navigationBarTitleText": "我的信用",
				"app-plus": {
					"scrollIndicator":"none",
					"titleNView": {
						"buttons": [{
							"text": "签到", //原生标题栏增加分享按钮，点击事件可通过页面的 onNavigationBarButtonTap 函数进行监听
							"fontSize": "26upx",
							"color": "#808080",
							"width": "150upx"
						}]
					}
				}
			}
		}, {
			"path": "pages/index/member-hall",
			"style": {
				"navigationBarTitleText": "会员大厅",
				"app-plus": {
					"scrollIndicator": "none",
					"bounce": "vertical"
				}
			}
		}, {
			"path": "pages/msg/msg-detail",
			"style": {
				"navigationBarTitleText": "消息详情",
				"app-plus": {
					"scrollIndicator": "none",
					"bounce": "vertical"
				}
			}
		}, {
			"path": "pages/profile/task-record",
			"style": {
				"navigationBarBackgroundColor": "#080d5d",
				"navigationBarTextStyle": "white",
				"navigationBarTitleText": "任务记录",
				"app-plus": {
					"scrollIndicator": "none",
					"bounce": "vertical"
				}
			}
		}, {
			"path": "pages/profile/submit-task",
			"style": {
				"navigationBarTitleText": "提交任务",
				"app-plus": {
					"scrollIndicator": "none",
					"bounce": "vertical"
				}
			}
		}, {
			"path": "pages/index/task-detail",
			"style": {
				"navigationBarTextStyle": "white",
				"navigationStyle": "custom",
				"app-plus": {
					"scrollIndicator": "none",
					"bounce": "vertical"
				}
			}
		}, {
			"path": "pages/index/guide",
			"style": {
				"navigationBarTitleText": "新手指南",
				"app-plus": {
					"scrollIndicator": "none",
					"bounce": "vertical"
				}
			}
		}, {
			"path": "pages/profile/open-member",
			"style": {
				"navigationBarTitleText": "开通会员",
				"app-plus": {
					"scrollIndicator":"none",
					"titleNView": {
						"buttons": [{
							"text": "充值记录", //原生标题栏增加分享按钮，点击事件可通过页面的 onNavigationBarButtonTap 函数进行监听
							"fontSize": "26upx",
							"color": "#808080",
							"width": "150upx"
						}]
					}
				}
			}
		}, {
			"path": "pages/profile/success-task",
			"style": {
				"navigationBarTitleText": "任务列表",
				"app-plus": {
					"scrollIndicator": "none",
					"bounce": "vertical"
				}
			}
		}, {
			"path": "pages/profile/my-credit",
			"style": {
				"navigationBarTitleText": "我的信用",
				"app-plus": {
					"scrollIndicator": "none",
					"bounce": "vertical"
				}
			}
		}, {
			"path": "pages/profile/credit-list",
			"style": {
				"navigationBarTitleText": "信用记录",
				"app-plus": {
					"scrollIndicator": "none",
					"bounce": "vertical"
				}
			}
		}, {
			"path": "pages/profile/task-detail",
			"style": {
				"navigationBarTitleText": "任务详情",
				"app-plus": {
					"scrollIndicator": "none",
					"bounce": "vertical"
				}
			}
		}, {
			"path": "pages/profile/account",
			"style": {
				"navigationBarTitleText": "提现账户",
				"app-plus": {
					"scrollIndicator": "none",
					"bounce": "vertical"
				}
			}
		}, {
			"path": "pages/profile/modify-name",
			"style": {
				"navigationBarTitleText": "修改名称",
				"app-plus": {
					"scrollIndicator":"none",
					"titleNView": {
						"buttons": [{
							"text": "保存", //原生标题栏增加分享按钮，点击事件可通过页面的 onNavigationBarButtonTap 函数进行监听
							"fontSize": "26upx",
							"color": "#808080",
							"width": "150upx"
						}]
					}
				}
			}
		}, {
			"path": "pages/index/not-open",
			"style": {
				"navigationBarTitleText": "暂未开放",
				"app-plus": {
					"scrollIndicator": "none",
					"bounce": "vertical"
				}
			}
		}, {
			"path": "pages/profile/invitation",
			"style": {
				"navigationStyle": "custom",
				"app-plus": {
					"scrollIndicator": "none",
					"bounce": "vertical"
				}
			}
		}, {
			"path": "pages/login/register",
			"style": {
				"navigationBarTitleText": "注册",
				"app-plus": {
					"scrollIndicator": "none",
					"bounce": "vertical"
				}
			}
		}, {
			"path": "pages/profile/withdraw-record",
			"style": {
				"navigationBarTitleText": "提现记录",
				"app-plus": {
					"scrollIndicator": "none",
					"bounce": "vertical"
				}
			}
		}, {
			"path": "pages/profile/scancode-pay",
			"style": {
				"navigationBarTitleText": "扫码支付",
				"navigationBarBackgroundColor": "#ffc000",
				"navigationBarTextStyle": "white",
				"app-plus": {
					"scrollIndicator": "none",
					"bounce": "vertical"
				}
			}
		}, {
			"path": "pages/profile/upload-image",
			"style": {
				"navigationBarTitleText": "上传账单",
				"app-plus": {
					"scrollIndicator": "none",
					"bounce": "vertical"
				}
			}
		}, {
			"path": "pages/profile/modify-number",
			"style": {
				"navigationBarTitleText": "修改手机号",
				"app-plus": {
					"scrollIndicator": "none",
					"bounce": "vertical"
				}
			}
		}, {
			"path": "pages/profile/my-bill",
			"style": {
				"navigationBarTitleText": "我的账单",
				"app-plus": {
					"scrollIndicator": "none",
					"bounce": "vertical"
				}
			}
		},
		{
			"path": "pages/profile/pay-record",
			"style": {
				"navigationBarTitleText": "充值记录",
				"app-plus": {
					"scrollIndicator": "none",
					"bounce": "vertical"
				}
			}
		}
	    ,{
            "path" : "pages/login/privacy-policy",
            "style" : {
				"navigationBarTitleText":"隐私政策",
				"app-plus": {
					"scrollIndicator": "none",
					"bounce": "vertical"
				}
			}
        }
        ,{
            "path" : "pages/login/usage-agreement",
            "style" : {
				"navigationBarTitleText":"协议",
				"app-plus": {
					"scrollIndicator": "none",
					"bounce": "vertical"
				}
			}
        }
        ,{
            "path" : "pages/profile/help-center",
            "style" : {
				"navigationBarTitleText":"帮助中心",
				"app-plus": {
					"scrollIndicator": "none",
					"bounce": "vertical"
				}
			}
        }
        ,{
            "path" : "pages/index/searchList",
            "style" : {
				"navigationBarTitleText":"搜索结果",
				"app-plus": {
					"scrollIndicator": "none",
					"bounce": "vertical"
				}
			}
        }
    ],
	"globalStyle": {
		"navigationBarTextStyle": "black",
		"navigationBarTitleText": "",
		"navigationBarBackgroundColor": "#FFFFFF",
		"backgroundColor": "#FFFFFF"
	},
	"tabBar": {
		"color": "#757575",
		"selectedColor": "#1b2664",
		"backgroundColor": "#ffffff",
		"borderStyle": "",
		"list": [{
				"pagePath": "pages/tabbar/index",
				"text": "首页",
				"iconPath": "static/images/tabbar/index.png",
				"selectedIconPath": "static/images/tabbar/index_active.png"
			},
			{
				"pagePath": "pages/tabbar/vip",
				"text": "VIP",
				"iconPath": "static/images/tabbar/vip.png",
				"selectedIconPath": "static/images/tabbar/vip_active.png"
			},
			{
				"pagePath": "pages/tabbar/msg",
				"text": "消息",
				"iconPath": "static/images/tabbar/msg.png",
				"selectedIconPath": "static/images/tabbar/msg_active.png"
			},
			{
				"pagePath": "pages/tabbar/profile",
				"text": "我的",
				"iconPath": "static/images/tabbar/profile.png",
				"selectedIconPath": "static/images/tabbar/profile_active.png"
			}
		]
	}
}
